{"389-exception": "389-exception", "Glide": "glide", "DOC": "ace-tao", "AMDPLPA": "amdplpa", "ANTLR-PD": "antlr-pd", "Abstyles": "abstyles", "AFL-1.1": "afl-1.1", "AFL-1.2": "afl-1.2", "AFL-2.0": "afl-2.0", "AFL-2.1": "afl-2.1", "AFL-3.0": "afl-3.0", "AMPAS": "ampas", "APL-1.0": "adapt-1.0", "Adobe-Glyph": "adobe-glyph", "APAFML": "apafml", "Adobe-2006": "adobe-scl", "AGPL-1.0-only": "agpl-1.0", "AGPL-1.0-or-later": "agpl-1.0-plus", "Aladdin": "afpl-8.0", "Giftware": "allegro-4", "Xnet": "xnet", "ADSL": "adsl", "Apache-1.0": "apache-1.0", "Apache-1.1": "apache-1.1", "Apache-2.0": "apache-2.0", "APSL-1.0": "apsl-1.0", "APSL-1.1": "apsl-1.1", "APSL-1.2": "apsl-1.2", "APSL-2.0": "apsl-2.0", "AML": "aml", "Artistic-1.0-Perl": "artistic-perl-1.0", "Artistic-1.0": "artistic-1.0", "Artistic-1.0-cl8": "artistic-1.0-cl8", "Artistic-2.0": "artistic-2.0", "AAL": "attribution", "Autoconf-exception-2.0": "autoconf-exception-2.0", "Autoconf-exception-3.0": "autoconf-exception-3.0", "BSD-3-Clause-No-Nuclear-Warranty": "bsd-3-clause-no-nuclear-warranty", "BSD-3-Clause-Open-MPI": "bsd-3-clause-open-mpi", "BSD-3-Clause-Attribution": "bsd-ack", "BSD-Protection": "bsd-protection", "BSD-Source-Code": "bsd-source-code", "0BSD": "bsd-zero", "BSD-1-Clause": "bsd-1-clause", "BSD-2-Clause": "bsd-simplified", "BSD-2-Clause-Patent": "bsd-plus-patent", "BSD-2-Clause-FreeBSD": "bsd-2-clause-freebsd", "BSD-2-Clause-NetBSD": "bsd-2-clause-netbsd", "BSD-3-Clause": "bsd-new", "BSD-4-Clause": "bsd-original", "BSD-4-Clause-UC": "bsd-original-uc", "Bahyph": "bahyph", "Barr": "barr-tex", "Beerware": "beerware", "Bison-exception-2.2": "bison-exception-2.2", "BitTorrent-1.0": "bittorrent-1.0", "BitTorrent-1.1": "bittorrent-1.1", "BlueOak-1.0.0": "blueoak-1.0.0", "BSL-1.0": "boost-1.0", "Bootloader-exception": "bootloader-exception", "Borceux": "borceux", "CERN-OHL-1.2": "cern-ohl-1.2", "CERN-OHL-1.1": "cern-ohl-1.1", "CLISP-exception-2.0": "clisp-exception-2.0", "CNRI-Jython": "cnri-jython", "CNRI-Python": "cnri-python-1.6", "CNRI-Python-GPL-Compatible": "cnri-python-1.6.1", "CUA-OPL-1.0": "cua-opl-1.0", "Caldera": "caldera", "MIT-CMU": "cmu-uc", "CECILL-1.0": "cecill-1.0", "CECILL-1.1": "cecill-1.1", "CECILL-2.0": "cecill-2.0", "CECILL-2.1": "cecill-2.1", "CECILL-B": "cecill-b", "CECILL-C": "cecill-c", "ClArtistic": "artistic-clarified", "Classpath-exception-2.0": "classpath-exception-2.0", "BSD-3-Clause-Clear": "clear-bsd", "CPOL-1.02": "cpol-1.02", "CDDL-1.0": "cddl-1.0", "CDDL-1.1": "cddl-1.1", "CPAL-1.0": "cpal-1.0", "CPL-1.0": "cpl-1.0", "CDLA-Permissive-1.0": "cdla-permissive-1.0", "CDLA-Sharing-1.0": "cdla-sharing-1.0", "CATOSL-1.1": "ca-tosl-1.1", "Condor-1.1": "condor-1.1", "CC-BY-4.0": "cc-by-4.0", "CC-BY-1.0": "cc-by-1.0", "CC-BY-2.0": "cc-by-2.0", "CC-BY-2.5": "cc-by-2.5", "CC-BY-3.0": "cc-by-3.0", "CC-BY-ND-1.0": "cc-by-nd-1.0", "CC-BY-ND-2.0": "cc-by-nd-2.0", "CC-BY-ND-2.5": "cc-by-nd-2.5", "CC-BY-ND-3.0": "cc-by-nd-3.0", "CC-BY-NC-1.0": "cc-by-nc-1.0", "CC-BY-NC-2.0": "cc-by-nc-2.0", "CC-BY-NC-2.5": "cc-by-nc-2.5", "CC-BY-NC-3.0": "cc-by-nc-3.0", "CC-BY-NC-ND-1.0": "cc-by-nc-nd-1.0", "CC-BY-NC-ND-2.0": "cc-by-nc-nd-2.0", "CC-BY-NC-ND-2.5": "cc-by-nc-nd-2.5", "CC-BY-NC-ND-3.0": "cc-by-nc-nd-3.0", "CC-BY-NC-SA-1.0": "cc-by-nc-sa-1.0", "CC-BY-NC-SA-2.0": "cc-by-nc-sa-2.0", "CC-BY-NC-SA-2.5": "cc-by-nc-sa-2.5", "CC-BY-NC-SA-3.0": "cc-by-nc-sa-3.0", "CC-BY-SA-1.0": "cc-by-sa-1.0", "CC-BY-SA-2.0": "cc-by-sa-2.0", "CC-BY-SA-2.5": "cc-by-sa-2.5", "CC-BY-SA-3.0": "cc-by-sa-3.0", "CC-BY-ND-4.0": "cc-by-nd-4.0", "CC-BY-NC-4.0": "cc-by-nc-4.0", "CC-BY-NC-ND-4.0": "cc-by-nc-nd-4.0", "CC-BY-NC-SA-4.0": "cc-by-nc-sa-4.0", "CC-BY-SA-4.0": "cc-by-sa-4.0", "CC0-1.0": "cc0-1.0", "CC-PDDC": "cc-pd", "Crossword": "crossword", "CrystalStacker": "crystal-stacker", "Cube": "cube", "DSDP": "dsdp", "D-FSL-1.0": "d-fsl-1.0-de", "DigiRule-FOSS-exception": "digirule-foss-exception", "Plexus": "dom4j", "Dotseqn": "dotseqn", "EUDatagrid": "eu-datagrid", "EPL-1.0": "epl-1.0", "EPL-2.0": "epl-2.0", "ECL-1.0": "ecl-1.0", "ECL-2.0": "ecl-2.0", "EFL-1.0": "efl-1.0", "EFL-2.0": "efl-2.0", "MIT-advertising": "enlightenment", "Entessa": "entessa-1.0", "ErlPL-1.1": "erlangpl-1.1", "EUPL-1.0": "eupl-1.0", "EUPL-1.1": "eupl-1.1", "EUPL-1.2": "eupl-1.2", "Eurosym": "eurosym", "FLTK-exception": "fltk-exception-lgpl-2.0", "FSFAP": "fsf-ap", "Fair": "fair", "OML": "fastcgi-devkit", "Fawkes-Runtime-exception": "fawkes-runtime-exception", "Font-exception-2.0": "font-exception-gpl", "Frameworx-1.0": "frameworx-1.0", "FSFUL": "fsf-free", "FSFULLR": "fsf-unlimited", "FreeImage": "freeimage-1.0", "freertos-exception-2.0": "freertos-exception-2.0", "FTL": "freetype", "GCC-exception-2.0": "gcc-linking-exception-2.0", "GCC-exception-3.1": "gcc-exception-3.1", "GL2PS": "gl2ps", "AGPL-3.0-only": "agpl-3.0", "AGPL-3.0-or-later": "agpl-3.0-plus", "GFDL-1.1-only": "gfdl-1.1", "GFDL-1.1-or-later": "gfdl-1.1-plus", "GFDL-1.2-only": "gfdl-1.2", "GFDL-1.2-or-later": "gfdl-1.2-plus", "GFDL-1.3-only": "gfdl-1.3", "GFDL-1.3-or-later": "gfdl-1.3-plus", "GPL-1.0-only": "gpl-1.0", "GPL-1.0-or-later": "gpl-1.0-plus", "GPL-2.0-only": "gpl-2.0", "GPL-2.0-or-later": "gpl-2.0-plus", "GPL-3.0-only": "gpl-3.0", "GPL-3.0-or-later": "gpl-3.0-plus", "gnu-javamail-exception": "gnu-javamail-exception", "LGPL-2.1-only": "lgpl-2.1", "LGPL-2.1-or-later": "lgpl-2.1-plus", "LGPL-3.0-only": "lgpl-3.0", "LGPL-3.0-or-later": "lgpl-3.0-plus", "LGPL-2.0-only": "lgpl-2.0", "LGPL-2.0-or-later": "lgpl-2.0-plus", "Libtool-exception": "libtool-exception-2.0", "GPL-2.0-with-GCC-exception": "gpl-2.0-gcc", "eCos-2.0": "ecos", "GPL-2.0-with-autoconf-exception": "gpl-2.0-autoconf", "GPL-2.0-with-classpath-exception": "gpl-2.0-classpath", "GPL-2.0-with-font-exception": "gpl-2.0-font", "GPL-3.0-with-autoconf-exception": "gpl-3.0-autoconf", "GPL-3.0-with-GCC-exception": "gpl-3.0-gcc", "GPL-CC-1.0": "gplcc-1.0", "Glulxe": "glulxe", "HaskellReport": "haskell-report", "Spencer-99": "henry-spencer-1999", "Spencer-94": "hs-regexp", "HPND": "historical", "IBM-pibs": "ibm-pibs", "IPL-1.0": "ibmpl-1.0", "IPA": "ipa-font", "ISC": "isc", "ImageMagick": "imagemagick", "Imlib2": "imlib2", "IJG": "ijg", "xpp": "indiana-extreme-1.2", "Info-ZIP": "info-zip", "Intel-ACPI": "intel-acpi", "Intel": "intel-bsd-export-control", "Interbase-1.0": "interbase-1.0", "JPNIC": "jpnic-idnkit", "JSON": "json", "JasPer-2.0": "jasper-2.0", "LLVM-exception": "llvm-exception", "LZMA-exception": "lzma-cpl-exception", "LPPL-1.0": "lppl-1.0", "LPPL-1.1": "lppl-1.1", "LPPL-1.2": "lppl-1.2", "LPPL-1.3a": "lppl-1.3a", "LPPL-1.3c": "lppl-1.3c", "Latex2e": "latex2e", "BSD-3-Clause-LBNL": "lbnl-bsd", "Leptonica": "leptonica", "LGPLLR": "lgpllr", "Libpng": "libpng", "LAL-1.2": "lal-1.2", "LAL-1.3": "lal-1.3", "LiLiQ-P-1.1": "liliq-p-1.1", "LiLiQ-Rplus-1.1": "liliq-rplus-1.1", "LiLiQ-R-1.1": "liliq-r-1.1", "Linux-syscall-note": "linux-syscall-exception-gpl", "Linux-OpenIB": "linux-openib", "LPL-1.0": "lucent-pl-1.0", "LPL-1.02": "lucent-pl-1.02", "MIT-feh": "mit-ack", "MIT": "mit", "MIT-0": "mit-0", "NTP": "mit-old-style-no-advert", "Xerox": "mit-export-control", "MITNFA": "mit-no-false-attribs", "mpich2": "mpich", "mif-exception": "mif-exception", "MakeIndex": "makeindex", "MTLL": "mtll", "MS-PL": "ms-pl", "MS-RL": "ms-rl", "MirOS": "mir-os", "SSPL-1.0": "mongodb-sspl-1.0", "Motosoto": "motosoto-0.9.1", "MPL-1.0": "mpl-1.0", "MPL-1.1": "mpl-1.1", "MPL-2.0": "mpl-2.0", "MPL-2.0-no-copyleft-exception": "mpl-2.0-no-copyleft-exception", "Multics": "multics", "Mup": "mup", "NASA-1.3": "nasa-1.3", "Naumen": "naumen", "NRL": "nrl", "NBPL-1.0": "nbpl-1.0", "Net-SNMP": "net-snmp", "NetCDF": "netcdf", "NGPL": "ngpl", "NOSL": "nosl-1.0", "NPL-1.0": "npl-1.0", "NPL-1.1": "npl-1.1", "Newsletr": "newsletr", "NLPL": "nlpl", "Nokia": "nokos-1.0a", "NPOSL-3.0": "nosl-3.0", "NLOD-1.0": "nlod-1.0", "Noweb": "noweb", "OCLC-2.0": "oclc-2.0", "OCaml-LGPL-linking-exception": "ocaml-lgpl-linking-exception", "ODbL-1.0": "odbl-1.0", "OSET-PL-2.1": "oset-pl-2.1", "OCCT-exception-1.0": "occt-exception-1.0", "OCCT-PL": "occt-pl", "ODC-By-1.0": "odc-by-1.0", "OGTSL": "opengroup", "OPL-1.0": "open-public", "OSL-1.0": "osl-1.0", "OSL-1.1": "osl-1.1", "OSL-2.0": "osl-2.0", "OSL-2.1": "osl-2.1", "OSL-3.0": "osl-3.0", "OpenJDK-assembly-exception-1.0": "openjdk-assembly-exception-1.0", "OLDAP-1.1": "openldap-1.1", "OLDAP-1.2": "openldap-1.2", "OLDAP-1.3": "openldap-1.3", "OLDAP-1.4": "openldap-1.4", "OLDAP-2.0": "openldap-2.0", "OLDAP-2.0.1": "openldap-2.0.1", "OLDAP-2.1": "openldap-2.1", "OLDAP-2.2": "openldap-2.2", "OLDAP-2.2.1": "openldap-2.2.1", "OLDAP-2.2.2": "openldap-2.2.2", "OLDAP-2.3": "openldap-2.3", "OLDAP-2.4": "openldap-2.4", "OLDAP-2.5": "openldap-2.5", "OLDAP-2.6": "openldap-2.6", "OLDAP-2.7": "openldap-2.7", "OLDAP-2.8": "openldap-2.8", "OpenSSL": "openssl-ssleay", "openvpn-openssl-exception": "openvpn-openssl-exception", "BSD-3-Clause-No-Nuclear-License-2014": "oracle-bsd-no-nuclear", "PHP-3.0": "php-3.0", "PHP-3.01": "php-3.01", "libpng-2.0": "libpng-v2", "psutils": "psutils", "PS-or-PDF-font-exception-20170817": "ps-or-pdf-font-exception-20170817", "PostgreSQL": "postgresql", "PDDL-1.0": "pddl-1.0", "Python-2.0": "python", "QPL-1.0": "qpl-1.0", "Qhull": "qhull", "Qt-GPL-exception-1.0": "qt-gpl-exception-1.0", "Qt-LGPL-exception-1.1": "qt-lgpl-exception-1.1", "Qwt-exception-1.0": "qwt-exception-1.0", "RSA-MD": "rsa-md5", "Rdisc": "rdisc", "RPSL-1.0": "rpsl-1.0", "RPL-1.1": "rpl-1.1", "RPL-1.5": "rpl-1.5", "RHeCos-1.1": "ecosrh-1.1", "Spencer-86": "regexp", "RSCPL": "ricoh-1.0", "Ruby": "ruby", "Swift-exception": "apple-runtime-library-exception", "SAX-PD": "sax-pd", "SCEA": "scea-1.0", "iMatix": "sfl-license", "SGI-B-1.0": "sgi-fslb-1.0", "SGI-B-1.1": "sgi-freeb-1.1", "SGI-B-2.0": "sgi-freeb-2.0", "OFL-1.0": "ofl-1.0", "OFL-1.1": "ofl-1.1", "SNIA": "snia", "blessing": "blessing", "Saxpath": "saxpath", "SWL": "swl", "SMPPL": "smppl", "Sendmail": "sendmail", "Sendmail-8.23": "sendmail-8.23", "SimPL-2.0": "simpl-2.0", "Sleepycat": "sleepycat", "SHL-0.5": "shl-0.5", "SHL-0.51": "shl-0.51", "SMLNJ": "standard-ml-nj", "SugarCRM-1.1.3": "sugarcrm-1.1.3", "BSD-3-Clause-No-Nuclear-License": "sun-bsd-no-nuclear", "SISSL": "sun-sissl-1.1", "SISSL-1.2": "sun-sissl-1.2", "SPL-1.0": "spl-1.0", "Watcom-1.0": "sybase", "TAPR-OHL-1.0": "tapr-ohl-1.0", "TCL": "tcl", "TCP-wrappers": "tcp-wrappers", "TMate": "tmate", "TORQUE-1.1": "torque-1.1", "TU-Berlin-1.0": "tu-berlin", "TU-Berlin-2.0": "tu-berlin-2.0", "Parity-6.0.0": "parity-6.0.0", "TOSL": "tosl", "u-boot-exception-2.0": "u-boot-exception-2.0", "OGL-UK-1.0": "ogl-uk-1.0", "OGL-UK-2.0": "ogl-uk-2.0", "OGL-UK-3.0": "ogl-uk-3.0", "Unicode-DFS-2015": "unicode-dfs-2015", "Unicode-DFS-2016": "unicode-dfs-2016", "Unicode-TOU": "unicode-tou", "Universal-FOSS-exception-1.0": "universal-foss-exception-1.0", "UPL-1.0": "upl-1.0", "NCSA": "uoi-ncsa", "Unlicense": "unlicense", "Vim": "vim", "VOSTROM": "vostrom", "VSL-1.0": "vsl-1.0", "W3C": "w3c", "W3C-19980720": "w3c-software-19980720", "W3C-20150513": "w3c-software-doc-20150513", "WTFPL": "wtfpl-2.0", "Wsuipa": "wsuipa", "WxWindows-exception-3.1": "wxwindows-exception-3.1", "ICU": "x11", "HPND-sell-variant": "x11-keith-packard", "libtiff": "x11-tiff", "X11": "x11-xconsortium", "XFree86-1.1": "xfree86-1.1", "XSkat": "xskat", "YPL-1.0": "ypl-1.0", "YPL-1.1": "ypl-1.1", "Zlib": "zlib", "zlib-acknowledgement": "zlib-acknowledgement", "Zed": "zed", "Zend-2.0": "zend-2.0", "Zimbra-1.3": "zimbra-1.3", "Zimbra-1.4": "zimbra-1.4", "ZPL-1.1": "zpl-1.1", "ZPL-2.0": "zpl-2.0", "ZPL-2.1": "zpl-2.1", "Afmparse": "afmparse", "bzip2-1.0.5": "bzip2-libbzip-1.0.5", "bzip2-1.0.6": "bzip2-libbzip-2010", "curl": "curl", "copyleft-next-0.3.0": "copyleft-next-0.3.0", "copyleft-next-0.3.1": "copyleft-next-0.3.1", "diffmark": "diffmark", "dvipdfm": "dvipdfm", "eCos-exception-2.0": "ecos-exception-2.0", "eGenix": "egenix-1.1.0", "MIT-enna": "enna", "gSOAP-1.3b": "gsoap-1.3b", "gnuplot": "gnuplot", "i2p-gpl-java-exception": "i2p-gpl-java-exception", "psfrag": "psfrag", "wxWindows": "wxwindows", "xinetd": "xinetd"}